nrp_protobuf/dump_pb2.py
nrp_protobuf/edlutdata_pb2.py
nrp_protobuf/engine_grpc_pb2.py
nrp_protobuf/engine_grpc_pb2_grpc.py
nrp_protobuf/enginetest_pb2.py
nrp_protobuf/gazebo_pb2.py
nrp_protobuf/nrp_server_pb2.py
nrp_protobuf/nrp_server_pb2_grpc.py
nrp_protobuf/nrpgenericproto_pb2.py
nrp_protobuf/proto_modules.py
nrp_protobuf/wrappers_pb2.py
nrp_protobuf-1.4.0.dist-info/METADATA
nrp_protobuf-1.4.0.dist-info/WHEEL
nrp_protobuf-1.4.0.dist-info/top_level.txt
nrp_protobuf-1.4.0.dist-info/RECORD
