Metadata-Version: 2.1
Name: nrp-protobuf
Version: 1.4.0
Summary: Python module for protobuf python definitions for the NRP-Core
Author: NRP Team
Author-email: vorobev@im.tum.de
Classifier: Programming Language :: Python :: 3
Requires-Python: >=3.8
Requires-Dist: psutil
Requires-Dist: grpcio-tools (>=1.49.1)
